setup.py
tenderloin/__init__.py
tenderloin/backend.py
tenderloin/cli.py
tenderloin/plugin.py
tenderloin/server.py
tenderloin.egg-info/PKG-INFO
tenderloin.egg-info/SOURCES.txt
tenderloin.egg-info/dependency_links.txt
tenderloin.egg-info/entry_points.txt
tenderloin.egg-info/not-zip-safe
tenderloin.egg-info/requires.txt
tenderloin.egg-info/top_level.txt