Metadata-Version: 1.0
Name: tenderloin
Version: 0.2.3
Summary: Tenderloin is a simple HTTP-based system information server
Home-page: UNKNOWN
Author: Scott Smith
Author-email: scott@ohlol.net
License: BSD
Platform: UNKNOWN
Classifier: Development Status :: 3 - Alpha
Classifier: Intended Audience :: System Administrators
Classifier: License :: OSI Approved :: BSD License
Classifier: Topic :: System :: Networking :: Monitoring
